PythonLianghuaJiaoyiJiaochengFix1/README.md
PythonLianghuaJiaoyiJiaochengFix1/__init__.py
PythonLianghuaJiaoyiJiaochengFix1/__main__.py
PythonLianghuaJiaoyiJiaochengFix1/file.epub
PythonLianghuaJiaoyiJiaochengFix1/index.html
PythonLianghuaJiaoyiJiaochengFix1/css/__init__.py
PythonLianghuaJiaoyiJiaochengFix1/css/annotations.css
PythonLianghuaJiaoyiJiaochengFix1/css/main.css
PythonLianghuaJiaoyiJiaochengFix1/css/normalize.css
PythonLianghuaJiaoyiJiaochengFix1/css/popup.css
PythonLianghuaJiaoyiJiaochengFix1/font/__init__.py
PythonLianghuaJiaoyiJiaochengFix1/font/fontello.eot
PythonLianghuaJiaoyiJiaochengFix1/font/fontello.svg
PythonLianghuaJiaoyiJiaochengFix1/font/fontello.ttf
PythonLianghuaJiaoyiJiaochengFix1/font/fontello.woff
PythonLianghuaJiaoyiJiaochengFix1/img/__init__.py
PythonLianghuaJiaoyiJiaochengFix1/img/annotator-glyph-sprite.png
PythonLianghuaJiaoyiJiaochengFix1/img/annotator-icon-sprite.png
PythonLianghuaJiaoyiJiaochengFix1/img/apple-touch-icon.png
PythonLianghuaJiaoyiJiaochengFix1/img/cancelfullscreen.png
PythonLianghuaJiaoyiJiaochengFix1/img/close.png
PythonLianghuaJiaoyiJiaochengFix1/img/fullscreen.png
PythonLianghuaJiaoyiJiaochengFix1/img/loader.gif
PythonLianghuaJiaoyiJiaochengFix1/img/menu-icon.png
PythonLianghuaJiaoyiJiaochengFix1/img/save.png
PythonLianghuaJiaoyiJiaochengFix1/img/saved.png
PythonLianghuaJiaoyiJiaochengFix1/img/settings-s.png
PythonLianghuaJiaoyiJiaochengFix1/img/settings.png
PythonLianghuaJiaoyiJiaochengFix1/img/star.png
PythonLianghuaJiaoyiJiaochengFix1/js/__init__.py
PythonLianghuaJiaoyiJiaochengFix1/js/epub.js
PythonLianghuaJiaoyiJiaochengFix1/js/epub.min.js
PythonLianghuaJiaoyiJiaochengFix1/js/epub.min.map
PythonLianghuaJiaoyiJiaochengFix1/js/hooks.min.js
PythonLianghuaJiaoyiJiaochengFix1/js/hooks.min.map
PythonLianghuaJiaoyiJiaochengFix1/js/reader.js
PythonLianghuaJiaoyiJiaochengFix1/js/reader.js.map
PythonLianghuaJiaoyiJiaochengFix1/js/reader.min.js
PythonLianghuaJiaoyiJiaochengFix1/js/reader.min.map
python_lianghua_jiaoyi_jiaocheng_fix1-2024.3.1.0.dist-info/METADATA
python_lianghua_jiaoyi_jiaocheng_fix1-2024.3.1.0.dist-info/WHEEL
python_lianghua_jiaoyi_jiaocheng_fix1-2024.3.1.0.dist-info/entry_points.txt
python_lianghua_jiaoyi_jiaocheng_fix1-2024.3.1.0.dist-info/top_level.txt
python_lianghua_jiaoyi_jiaocheng_fix1-2024.3.1.0.dist-info/RECORD
